timekiller/timekiller.py
process_time_killer-0.2.dist-info/METADATA
process_time_killer-0.2.dist-info/WHEEL
process_time_killer-0.2.dist-info/entry_points.txt
process_time_killer-0.2.dist-info/RECORD
