Metadata-Version: 2.1
Name: process-time-killer
Version: 0.2
Summary: ⏰ process-time-killer
Author: Andrew A Levin
Author-email: your.email@example.com
Requires-Python: >=3.9
Classifier: Programming Language :: Python :: 3
Classifier: Programming Language :: Python :: 3.9
Classifier: Programming Language :: Python :: 3.10
Classifier: Programming Language :: Python :: 3.11
Classifier: Programming Language :: Python :: 3.12
Classifier: Programming Language :: Python :: 3.13
